README
setup.py
test/test_createtemplate.py
test/test_listavailableproducttypes.py
test/test_listvirtualmachines.py
ucloudbiz/__init__.py
ucloudbiz.egg-info/PKG-INFO
ucloudbiz.egg-info/SOURCES.txt
ucloudbiz.egg-info/dependency_links.txt
ucloudbiz.egg-info/top_level.txt
ucloudbiz.egg-info/zip-safe
ucloudbiz/server/__init__.py
ucloudbiz/server/account/__init__.py
ucloudbiz/server/account/listaccounts.py
ucloudbiz/server/address/__init__.py
ucloudbiz/server/address/associateipaddress.py
ucloudbiz/server/address/listpublicipaddresses.py
ucloudbiz/server/lib/__init__.py
ucloudbiz/server/lib/api.py
ucloudbiz/server/lib/queryAsyncJobResult.py
ucloudbiz/server/portforwarding/__init__.py
ucloudbiz/server/portforwarding/createfirewallrule.py
ucloudbiz/server/portforwarding/createportforwardingrule.py
ucloudbiz/server/portforwarding/listfirewallrules.py
ucloudbiz/server/portforwarding/listportforwardingrules.py
ucloudbiz/server/template/__init__.py
ucloudbiz/server/template/createtemplate.py
ucloudbiz/server/template/deletetemplate.py
ucloudbiz/server/template/listtemplates.py
ucloudbiz/server/template/updatetemplate.py
ucloudbiz/server/vm/__init__.py
ucloudbiz/server/vm/deployvirtualmachine.py
ucloudbiz/server/vm/listavailableproducttypes.py
ucloudbiz/server/vm/listvirtualmachines.py
ucloudbiz/server/volume/__init__.py
ucloudbiz/server/volume/listvolumes.py