Metadata-Version: 1.0
Name: ucloudbiz
Version: 0.3.1
Summary: ucloudbiz openapi python library.
Home-page: http://ucloud.googlecode.com
Author: Choonho Son
Author-email: choonho.son@kt.com
License: BSD
Keywords: ucloud ucloudbiz config library
Platform: UNKNOWN
Classifier: Topic :: Utilities
Classifier: License :: OSI Approved :: BSD License
